pytorch-monitor/__init__.py
pytorch-monitor/monitor.py
pytorch_monitor/__init__.py
pytorch_monitor/fig2img.py
pytorch_monitor/init_experiment.py
pytorch_monitor/monitor.py
pytorch_monitor-0.15.dist-info/DESCRIPTION.rst
pytorch_monitor-0.15.dist-info/METADATA
pytorch_monitor-0.15.dist-info/RECORD
pytorch_monitor-0.15.dist-info/WHEEL
pytorch_monitor-0.15.dist-info/metadata.json
pytorch_monitor-0.15.dist-info/top_level.txt
