Metadata-Version: 2.0
Name: pytorch-monitor
Version: 0.15
Summary: Monitor pytorch modules with minimal code.
Home-page: https://github.com/teffland/pytorch-monitor
Author: Tom Effland
Author-email: teffland@cs.columbia.edu
License: MIT
Download-URL: https://github.com/teffland/pytorch-monitor/archive/0.15.tar.gz
Keywords: pytorch,logging
Platform: UNKNOWN
Requires-Python: >=3
Requires-Dist: sh
Requires-Dist: tensorboardX
Requires-Dist: tensorflow (==1.6)
